{
  "_note": "40 郡草稿（2026-07-17）。以三國志 I 的 58 國砍併而成。座標為 SVG 節點圖用（viewBox 1000x820，x 向東、y 向南）。farm/trade 為 1-5 潛力階，決定開發度上限。鄰接關係為無向圖，兩側都要列。",
  "provinces": [
    { "id": "xiangping", "name": "襄平", "zhou": "幽州", "x": 870, "y": 120, "farm": 1, "trade": 2, "neighbors": ["beiping"] },
    { "id": "beiping",   "name": "北平", "zhou": "幽州", "x": 760, "y": 150, "farm": 2, "trade": 1, "neighbors": ["xiangping", "ji"] },
    { "id": "ji",        "name": "薊",   "zhou": "幽州", "x": 680, "y": 170, "farm": 3, "trade": 2, "neighbors": ["beiping", "nanpi", "changshan"] },
    { "id": "nanpi",     "name": "南皮", "zhou": "冀州", "x": 700, "y": 240, "farm": 3, "trade": 2, "neighbors": ["ji", "ye", "pingyuan"] },
    { "id": "changshan", "name": "常山", "zhou": "冀州", "x": 600, "y": 220, "farm": 2, "trade": 1, "neighbors": ["ji", "jinyang", "ye"] },
    { "id": "ye",        "name": "鄴",   "zhou": "冀州", "x": 620, "y": 290, "farm": 5, "trade": 3, "neighbors": ["changshan", "nanpi", "pingyuan", "puyang", "henei"] },
    { "id": "jinyang",   "name": "晉陽", "zhou": "并州", "x": 520, "y": 230, "farm": 2, "trade": 1, "neighbors": ["changshan", "henei", "changan"] },
    { "id": "pingyuan",  "name": "平原", "zhou": "青州", "x": 700, "y": 300, "farm": 3, "trade": 2, "neighbors": ["nanpi", "ye", "beihai", "puyang"] },
    { "id": "beihai",    "name": "北海", "zhou": "青州", "x": 800, "y": 300, "farm": 2, "trade": 2, "neighbors": ["pingyuan", "langya"] },
    { "id": "puyang",    "name": "濮陽", "zhou": "兗州", "x": 650, "y": 340, "farm": 3, "trade": 2, "neighbors": ["ye", "pingyuan", "chenliu"] },
    { "id": "chenliu",   "name": "陳留", "zhou": "兗州", "x": 620, "y": 380, "farm": 4, "trade": 3, "neighbors": ["puyang", "luoyang", "xuchang", "qiao", "xiaopei"] },
    { "id": "henei",     "name": "河內", "zhou": "司隸", "x": 570, "y": 320, "farm": 3, "trade": 2, "neighbors": ["ye", "jinyang", "luoyang"] },
    { "id": "luoyang",   "name": "洛陽", "zhou": "司隸", "x": 520, "y": 370, "farm": 3, "trade": 5, "neighbors": ["henei", "chenliu", "xuchang", "changan", "wan"] },
    { "id": "changan",   "name": "長安", "zhou": "司隸", "x": 400, "y": 380, "farm": 3, "trade": 4, "neighbors": ["luoyang", "jinyang", "tianshui", "hanzhong", "wan"] },
    { "id": "xuchang",   "name": "許昌", "zhou": "豫州", "x": 600, "y": 420, "farm": 5, "trade": 3, "neighbors": ["luoyang", "chenliu", "runan", "wan"] },
    { "id": "runan",     "name": "汝南", "zhou": "豫州", "x": 650, "y": 470, "farm": 4, "trade": 2, "neighbors": ["xuchang", "qiao", "shouchun", "jiangxia"] },
    { "id": "qiao",      "name": "譙",   "zhou": "豫州", "x": 700, "y": 430, "farm": 3, "trade": 2, "neighbors": ["chenliu", "runan", "xiaopei", "shouchun"] },
    { "id": "xiaopei",   "name": "小沛", "zhou": "徐州", "x": 740, "y": 400, "farm": 2, "trade": 2, "neighbors": ["chenliu", "qiao", "xiapi", "langya"] },
    { "id": "langya",    "name": "琅琊", "zhou": "徐州", "x": 790, "y": 360, "farm": 2, "trade": 1, "neighbors": ["beihai", "xiaopei", "xiapi"] },
    { "id": "xiapi",     "name": "下邳", "zhou": "徐州", "x": 780, "y": 420, "farm": 3, "trade": 3, "neighbors": ["xiaopei", "langya", "shouchun"] },
    { "id": "shouchun",  "name": "壽春", "zhou": "揚州", "x": 720, "y": 480, "farm": 4, "trade": 3, "neighbors": ["runan", "qiao", "xiapi", "lujiang", "jianye"] },
    { "id": "lujiang",   "name": "廬江", "zhou": "揚州", "x": 740, "y": 530, "farm": 2, "trade": 2, "neighbors": ["shouchun", "jianye", "chaisang", "jiangxia"] },
    { "id": "jianye",    "name": "建業", "zhou": "揚州", "x": 820, "y": 520, "farm": 3, "trade": 4, "neighbors": ["shouchun", "lujiang", "wu"] },
    { "id": "wu",        "name": "吳",   "zhou": "揚州", "x": 870, "y": 560, "farm": 3, "trade": 3, "neighbors": ["jianye", "kuaiji"] },
    { "id": "kuaiji",    "name": "會稽", "zhou": "揚州", "x": 860, "y": 620, "farm": 2, "trade": 2, "neighbors": ["wu", "chaisang"] },
    { "id": "chaisang",  "name": "柴桑", "zhou": "揚州", "x": 700, "y": 580, "farm": 2, "trade": 2, "neighbors": ["lujiang", "kuaiji", "jiangxia", "changsha"] },
    { "id": "wan",       "name": "宛",   "zhou": "荊州", "x": 540, "y": 450, "farm": 4, "trade": 3, "neighbors": ["luoyang", "changan", "xuchang", "xiangyang"] },
    { "id": "xiangyang", "name": "襄陽", "zhou": "荊州", "x": 520, "y": 510, "farm": 3, "trade": 3, "neighbors": ["wan", "shangyong", "jiangling", "jiangxia"] },
    { "id": "shangyong", "name": "上庸", "zhou": "荊州", "x": 440, "y": 470, "farm": 1, "trade": 1, "neighbors": ["xiangyang", "hanzhong"] },
    { "id": "jiangling", "name": "江陵", "zhou": "荊州", "x": 540, "y": 570, "farm": 3, "trade": 3, "neighbors": ["xiangyang", "jiangxia", "wuling", "changsha", "jiangzhou"] },
    { "id": "jiangxia",  "name": "江夏", "zhou": "荊州", "x": 630, "y": 550, "farm": 2, "trade": 2, "neighbors": ["runan", "xiangyang", "jiangling", "chaisang", "lujiang", "changsha"] },
    { "id": "changsha",  "name": "長沙", "zhou": "荊州", "x": 620, "y": 640, "farm": 3, "trade": 2, "neighbors": ["chaisang", "jiangxia", "jiangling", "wuling", "jiaozhi"] },
    { "id": "wuling",    "name": "武陵", "zhou": "荊州", "x": 520, "y": 640, "farm": 1, "trade": 1, "neighbors": ["jiangling", "changsha"] },
    { "id": "jiaozhi",   "name": "交趾", "zhou": "交州", "x": 560, "y": 760, "farm": 1, "trade": 2, "neighbors": ["changsha", "jianning"] },
    { "id": "hanzhong",  "name": "漢中", "zhou": "益州", "x": 360, "y": 450, "farm": 3, "trade": 1, "neighbors": ["changan", "shangyong", "chengdu", "tianshui"] },
    { "id": "chengdu",   "name": "成都", "zhou": "益州", "x": 280, "y": 540, "farm": 5, "trade": 3, "neighbors": ["hanzhong", "jiangzhou", "jianning"] },
    { "id": "jiangzhou", "name": "江州", "zhou": "益州", "x": 360, "y": 580, "farm": 2, "trade": 2, "neighbors": ["chengdu", "jiangling", "jianning"] },
    { "id": "jianning",  "name": "建寧", "zhou": "益州", "x": 300, "y": 700, "farm": 1, "trade": 1, "neighbors": ["chengdu", "jiangzhou", "jiaozhi"] },
    { "id": "tianshui",  "name": "天水", "zhou": "涼州", "x": 300, "y": 350, "farm": 2, "trade": 1, "neighbors": ["changan", "hanzhong", "wuwei"] },
    { "id": "wuwei",     "name": "武威", "zhou": "涼州", "x": 200, "y": 280, "farm": 1, "trade": 2, "neighbors": ["tianshui"] }
  ]
}
